nemoize/__init__.py
nemoize/memoize.py
nemoize-0.1.0.dist-info/LICENSE
nemoize-0.1.0.dist-info/WHEEL
nemoize-0.1.0.dist-info/METADATA
nemoize-0.1.0.dist-info/RECORD
