Metadata-Version: 2.1
Name: nemoize
Version: 0.1.0
Summary: Decorator utility to memoize a class, function, or method
Home-page: https://github.com/spoorn/nemoize
License: MIT
Keywords: memoize,utility,decorator,decorators
Author: spoorn
Author-email: spookump@gmail.com
Requires-Python: >=3.7,<4.0
Classifier: License :: OSI Approved :: MIT License
Classifier: Programming Language :: Python
Classifier: Programming Language :: Python :: 3
Classifier: Programming Language :: Python :: 3.7
Classifier: Programming Language :: Python :: 3.8
Classifier: Programming Language :: Python :: 3.9
Classifier: Programming Language :: Python :: 3.10
Classifier: Programming Language :: Python :: 3
Classifier: Topic :: Software Development :: Code Generators
Classifier: Topic :: Software Development :: Libraries
Classifier: Topic :: Software Development :: Libraries :: Python Modules
Project-URL: Repository, https://github.com/spoorn/nemoize
